codeanalyzer/__init__.py
codeanalyzer/__main__.py
codeanalyzer/core.py
codeanalyzer/py.typed
codeanalyzer/config/__init__.py
codeanalyzer/config/config.py
codeanalyzer/jedi/__init__.py
codeanalyzer/jedi/jedi.py
codeanalyzer/options/__init__.py
codeanalyzer/options/options.py
codeanalyzer/schema/__init__.py
codeanalyzer/schema/py_schema.py
codeanalyzer/semantic_analysis/__init__.py
codeanalyzer/semantic_analysis/codeql/__init__.py
codeanalyzer/semantic_analysis/codeql/codeql_analysis.py
codeanalyzer/semantic_analysis/codeql/codeql_exceptions.py
codeanalyzer/semantic_analysis/codeql/codeql_loader.py
codeanalyzer/semantic_analysis/codeql/codeql_query_runner.py
codeanalyzer/semantic_analysis/wala/__init__.py
codeanalyzer/syntactic_analysis/__init__.py
codeanalyzer/syntactic_analysis/exceptions.py
codeanalyzer/syntactic_analysis/symbol_table_builder.py
codeanalyzer/utils/__init__.py
codeanalyzer/utils/logging.py
codeanalyzer/utils/progress_bar.py
codeanalyzer_python-0.1.13.dist-info/METADATA
codeanalyzer_python-0.1.13.dist-info/WHEEL
codeanalyzer_python-0.1.13.dist-info/entry_points.txt
codeanalyzer_python-0.1.13.dist-info/licenses/LICENSE
codeanalyzer_python-0.1.13.dist-info/licenses/NOTICE
codeanalyzer_python-0.1.13.dist-info/RECORD
