Metadata-Version: 2.4
Name: codeanalyzer-python
Version: 0.1.13
Summary: Static Analysis on Python source code using Jedi, CodeQL and Treesitter.
Author-email: Rahul Krishna <i.m.ralk@gmail.com>
License-File: LICENSE
License-File: NOTICE
Requires-Python: >=3.9
Requires-Dist: jedi<0.20.0,>=0.18.0; python_version < '3.11'
Requires-Dist: jedi<=0.19.2; python_version >= '3.11'
Requires-Dist: msgpack<1.0.7,>=1.0.0; python_version < '3.11'
Requires-Dist: msgpack<2.0.0,>=1.0.7; python_version >= '3.11'
Requires-Dist: networkx<3.2.0,>=2.6.0; python_version < '3.11'
Requires-Dist: networkx<4.0.0,>=3.0.0; python_version >= '3.11'
Requires-Dist: numpy<1.24.0,>=1.21.0; python_version < '3.11'
Requires-Dist: numpy<2.0.0,>=1.24.0; python_version >= '3.11' and python_version < '3.12'
Requires-Dist: numpy<2.0.0,>=1.26.0; python_version >= '3.12'
Requires-Dist: packaging>=25.0
Requires-Dist: pandas<2.0.0,>=1.3.0; python_version < '3.11'
Requires-Dist: pandas<3.0.0,>=2.0.0; python_version >= '3.11'
Requires-Dist: pydantic<2.0.0,>=1.8.0; python_version < '3.11'
Requires-Dist: pydantic<3.0.0,>=2.0.0; python_version >= '3.11'
Requires-Dist: ray<3.0.0,>=2.10.0; python_version >= '3.11'
Requires-Dist: ray==2.0.0; python_version < '3.11'
Requires-Dist: requests<3.0.0,>=2.20.0; python_version >= '3.11'
Requires-Dist: rich<14.0.0,>=12.6.0; python_version < '3.11'
Requires-Dist: rich<15.0.0,>=14.0.0; python_version >= '3.11'
Requires-Dist: typer<1.0.0,>=0.9.0; python_version < '3.11'
Requires-Dist: typer<2.0.0,>=0.9.0; python_version >= '3.11'
Requires-Dist: typing-extensions<5.0.0,>=4.0.0; python_version < '3.11'
Requires-Dist: typing-extensions<6.0.0,>=4.5.0; python_version >= '3.11'
